baidu_mcp_server/__init__.py
baidu_mcp_server/server.py
iflow_mcp_baidu_mcp_server-0.1.7.dist-info/METADATA
iflow_mcp_baidu_mcp_server-0.1.7.dist-info/WHEEL
iflow_mcp_baidu_mcp_server-0.1.7.dist-info/entry_points.txt
iflow_mcp_baidu_mcp_server-0.1.7.dist-info/licenses/LICENSE
iflow_mcp_baidu_mcp_server-0.1.7.dist-info/RECORD
