Metadata-Version: 2.4
Name: iflow-mcp_baidu-mcp-server
Version: 0.1.7
Summary: MCP Server for searching via Baidu
Project-URL: Homepage, https://github.com/Evilran/baidu-mcp-server
Project-URL: Issues, https://github.com/Evilran/baidu-mcp-server/issues
Author: Evilran
License-File: LICENSE
Classifier: Development Status :: 3 - Alpha
Classifier: Intended Audience :: Developers
Classifier: License :: OSI Approved :: MIT License
Classifier: Programming Language :: Python :: 3
Classifier: Programming Language :: Python :: 3.10
Classifier: Programming Language :: Python :: 3.11
Classifier: Programming Language :: Python :: 3.12
Classifier: Programming Language :: Python :: 3.13
Requires-Python: >=3.10
Requires-Dist: beautifulsoup4>=4.13.3
Requires-Dist: httpx>=0.28.1
Requires-Dist: markdownify>=1.1.0
Requires-Dist: mcp[cli]>=1.3.0
Requires-Dist: playwright
Requires-Dist: readabilipy>=0.3.0
